README.md
setup.cfg
setup.py
pypif/__init__.py
pypif/pif.py
pypif.egg-info/PKG-INFO
pypif.egg-info/SOURCES.txt
pypif.egg-info/dependency_links.txt
pypif.egg-info/requires.txt
pypif.egg-info/top_level.txt
pypif/obj/__init__.py
pypif/obj/common/__init__.py
pypif/obj/common/classification.py
pypif/obj/common/display_item.py
pypif/obj/common/file_reference.py
pypif/obj/common/id.py
pypif/obj/common/instrument.py
pypif/obj/common/license.py
pypif/obj/common/method.py
pypif/obj/common/name.py
pypif/obj/common/pages.py
pypif/obj/common/person.py
pypif/obj/common/pio.py
pypif/obj/common/process_step.py
pypif/obj/common/property.py
pypif/obj/common/quantity.py
pypif/obj/common/rcl.py
pypif/obj/common/reference.py
pypif/obj/common/scalar.py
pypif/obj/common/software.py
pypif/obj/common/source.py
pypif/obj/common/value.py
pypif/obj/system/__init__.py
pypif/obj/system/system.py
pypif/obj/system/chemical/__init__.py
pypif/obj/system/chemical/chemical_system.py
pypif/obj/system/chemical/alloy/__init__.py
pypif/obj/system/chemical/alloy/alloy.py
pypif/obj/system/chemical/alloy/alloy_phase.py
pypif/obj/system/chemical/common/__init__.py
pypif/obj/system/chemical/common/composition.py
pypif/util/__init__.py
pypif/util/case.py
pypif/util/pif_encoder.py
pypif/util/serializable.py