Metadata-Version: 1.0
Name: pypif
Version: 2.1.1
Summary: Python tools for working with the Physical Information File (PIF)
Home-page: http://github.com/CitrineInformatics/pypif
Author: Kyle Michel
Author-email: kyle@citrine.io
License: UNKNOWN
Platform: UNKNOWN
